django_fernet/__init__.py
django_fernet/apps.py
django_fernet/fernet.py
django_fernet/fields.py
django_fernet-1.0.1.dist-info/LICENSE
django_fernet-1.0.1.dist-info/METADATA
django_fernet-1.0.1.dist-info/WHEEL
django_fernet-1.0.1.dist-info/top_level.txt
django_fernet-1.0.1.dist-info/RECORD
