Metadata-Version: 2.1
Name: django-fernet
Version: 1.0.1
Summary: Django model fields that store the values encrypted using Fernet.
Home-page: https://github.com/anexia/django-fernet
Author: Andreas Stocker
Author-email: AStocker@anexia-it.com
License: MIT
Classifier: Development Status :: 5 - Production/Stable
Classifier: Framework :: Django
Classifier: Framework :: Django :: 4.2
Classifier: Framework :: Django :: 5.0
Classifier: Framework :: Django :: 5.1
Classifier: Intended Audience :: Developers
Classifier: License :: OSI Approved :: MIT License
Classifier: Operating System :: OS Independent
Classifier: Programming Language :: Python
Classifier: Programming Language :: Python :: 3
Classifier: Programming Language :: Python :: 3.10
Classifier: Programming Language :: Python :: 3.11
Classifier: Programming Language :: Python :: 3.12
Classifier: Programming Language :: Python :: 3.13
License-File: LICENSE
Requires-Dist: django>=4.2
Requires-Dist: cryptography>=43.0
